dwind/__init__.py
dwind/btm_sizing.py
dwind/config.py
dwind/loader.py
dwind/main.py
dwind/model.py
dwind/mp.py
dwind/resource.py
dwind/scenarios.py
dwind/valuation.py
dwind/cli/__init__.py
dwind/cli/collect.py
dwind/cli/debug.py
dwind/cli/run.py
dwind/cli/utils.py
dwind/utils/__init__.py
dwind/utils/array.py
dwind/utils/hpc.py
dwind/utils/loader.py
dwind-0.3.3.dist-info/licenses/LICENSE.txt
dwind-0.3.3.dist-info/METADATA
dwind-0.3.3.dist-info/WHEEL
dwind-0.3.3.dist-info/entry_points.txt
dwind-0.3.3.dist-info/top_level.txt
dwind-0.3.3.dist-info/RECORD
