Metadata-Version: 2.4
Name: dwind
Version: 0.3.3
Summary: Distributed Wind Generation Model
Author-email: Jane Lockshin <jane.lockshin@nrel.gov>, Paritosh Das <paritosh.das@nrel.gov>, Rob Hammond <rob.hammond@nrel.gov>
Project-URL: source, https://github.com/NREL/dwind
Project-URL: issues, https://github.com/NREL/dwind/issues
Project-URL: documentation, https://nrel.github.io/dwind/
Project-URL: changelog, https://github.com/NREL/dwind/blob/main/CHANGELOG.md
Keywords: python3,wind-energy,distributed-wind,energy-production
Classifier: Development Status :: 4 - Beta
Classifier: Intended Audience :: Science/Research
Classifier: Natural Language :: English
Classifier: Operating System :: OS Independent
Classifier: Programming Language :: Python
Classifier: Programming Language :: Python :: 3 :: Only
Classifier: Programming Language :: Python :: 3.11
Classifier: Programming Language :: Python :: 3.12
Classifier: Programming Language :: Python :: 3.13
Classifier: Topic :: Scientific/Engineering
Classifier: Topic :: Software Development :: Libraries :: Python Modules
Classifier: Typing :: Typed
Requires-Python: >=3.11
License-File: LICENSE.txt
Requires-Dist: nrel-rex
Requires-Dist: numpy
Requires-Dist: pandas>=2
Requires-Dist: sqlalchemy
Requires-Dist: psycopg2
Requires-Dist: scipy
Requires-Dist: matplotlib
Requires-Dist: seaborn
Requires-Dist: pyarrow==17
Requires-Dist: fastparquet
Requires-Dist: h5pyd
Requires-Dist: typer
Requires-Dist: rich
Requires-Dist: tomli>=1.1.0; python_version < "3.11"
Provides-Extra: dev
Requires-Dist: pre-commit; extra == "dev"
Requires-Dist: isort; extra == "dev"
Requires-Dist: ruff; extra == "dev"
Requires-Dist: pytest; extra == "dev"
Requires-Dist: pytest-cov; extra == "dev"
Requires-Dist: jupyter-book; extra == "dev"
Requires-Dist: sphinx-autodoc-typehints; extra == "dev"
Dynamic: license-file
